scrapy_camoufox/__init__.py
scrapy_camoufox/_utils.py
scrapy_camoufox/handler.py
scrapy_camoufox/memusage.py
scrapy_camoufox/page.py
scrapy_camoufox-0.0.12.dist-info/LICENSE
scrapy_camoufox-0.0.12.dist-info/METADATA
scrapy_camoufox-0.0.12.dist-info/WHEEL
scrapy_camoufox-0.0.12.dist-info/RECORD
