Metadata-Version: 2.3
Name: scrapy-camoufox
Version: 0.0.12
Summary: Camoufox Integration For Scrapy
Author: Ehsan U.
Requires-Python: >=3.9,<4.0
Classifier: Programming Language :: Python :: 3
Classifier: Programming Language :: Python :: 3.9
Classifier: Programming Language :: Python :: 3.10
Classifier: Programming Language :: Python :: 3.11
Classifier: Programming Language :: Python :: 3.12
Classifier: Programming Language :: Python :: 3.13
Requires-Dist: Scrapy (>=2.12.0,<3.0.0)
Requires-Dist: camoufox[geoip] (>=0.4.3,<0.5.0)
Requires-Dist: playwright (>=1.49.0,<2.0.0)
